{
    "x": -3257.736723188981,
    "y": 6569.155628303024,
    "z": 100,
    "guiLayer": "tile",
    "sheet": {
        "type": "",
        "id": "azasim",
        "id": "./SceneFiles/Menzoberranzan/DocumentsFiles/azasim",
        "page": "Document",
        "source": "",
        "name": "azasim",
        "img": "images/icons/pin.webp"
    },
    "texture": "images/icons/pin.webp",
    "scale": {
        "x": 100,
        "y": 100,
        "z": 1
    },
    "tile_id": "images_icons_pinwebp_34171b5c231d432e9aa372c2396ee4ba",
    "tile_json": "SceneFiles\\Menzoberranzan\\tag_images_icons_pinwebp_34171b5c231d432e9aa372c2396ee4ba_.json",
    "reference": {
        "type": "",
        "id": "azasim",
        "id": "./SceneFiles/Menzoberranzan/DocumentsFiles/azasim",
        "page": "Document",
        "source": "",
        "name": "azasim",
        "img": "images/icons/pin.webp"
    }
}